judge0_api_wrapper/__init__.py
judge0_api_wrapper/custom_types.py
judge0_api_wrapper/exceptions.py
judge0_api_wrapper/judge0.py
judge0_api_wrapper/schemas.py
judge0_api_wrapper-1.1.3.dist-info/licenses/LICENSE
judge0_api_wrapper-1.1.3.dist-info/METADATA
judge0_api_wrapper-1.1.3.dist-info/WHEEL
judge0_api_wrapper-1.1.3.dist-info/top_level.txt
judge0_api_wrapper-1.1.3.dist-info/RECORD
